SkitterCrawler/__init__.py
SkitterCrawler/random_walker_crawler.py
SkitterCrawler/twitter_crawlers.py
SkitterCrawler/util.py
SkitterCrawler-0.0.6.dist-info/DESCRIPTION.rst
SkitterCrawler-0.0.6.dist-info/METADATA
SkitterCrawler-0.0.6.dist-info/RECORD
SkitterCrawler-0.0.6.dist-info/WHEEL
SkitterCrawler-0.0.6.dist-info/entry_points.txt
SkitterCrawler-0.0.6.dist-info/metadata.json
SkitterCrawler-0.0.6.dist-info/top_level.txt
