Metadata-Version: 2.0
Name: SkitterCrawler
Version: 0.0.6
Summary: Generic packages with Crawlers for OSNs
Home-page: https://github.com/manoelhortaribeiro/SkitterCrawler
Author: Manoel Horta Ribeiro
Author-email: manoelhortaribeiro@gmail.com
License: MIT
Download-URL: https://github.com/manoelhortaribeiro/SkitterCrawler
Keywords: Online social network crawler utilities
Platform: UNKNOWN
Requires-Dist: SkitterSchema
Requires-Dist: numpy
Requires-Dist: sqlalchemy
Requires-Dist: tweepy
